cervo/__init__.py
cervo-0.0.1.dev0.dist-info/WHEEL
cervo-0.0.1.dev0.dist-info/METADATA
cervo-0.0.1.dev0.dist-info/RECORD
